pybart/__init__.py
pybart/api.py
pybart/draw.py
pybart/main.py
pybart/settings.py
pybart/utils.py
pybart-1.5.1.dist-info/DESCRIPTION.rst
pybart-1.5.1.dist-info/METADATA
pybart-1.5.1.dist-info/RECORD
pybart-1.5.1.dist-info/WHEEL
pybart-1.5.1.dist-info/entry_points.txt
pybart-1.5.1.dist-info/metadata.json
pybart-1.5.1.dist-info/top_level.txt
