Metadata-Version: 2.0
Name: pybart
Version: 1.5.1
Summary: Real time BART (Bay Area Rapid Transit) information in your terminal!
Home-page: https://github.com/ericdwang/pybart
Author: Eric Wang
Author-email: gnawrice@gmail.com
License: BSD 3-Clause
Keywords: bart,bay,area,rapid,transit
Platform: UNKNOWN
Classifier: Environment :: Console :: Curses
Classifier: Intended Audience :: End Users/Desktop
Classifier: License :: OSI Approved :: BSD License
Classifier: Natural Language :: English
Classifier: Operating System :: MacOS :: MacOS X
Classifier: Operating System :: POSIX :: Linux
Classifier: Programming Language :: Python :: 2
Classifier: Programming Language :: Python :: 3
